cxslogging/__init__.py
cxslogging/cxslog.py
cxs_logging_cxstoolbox-0.0.16.dist-info/LICENSE
cxs_logging_cxstoolbox-0.0.16.dist-info/METADATA
cxs_logging_cxstoolbox-0.0.16.dist-info/WHEEL
cxs_logging_cxstoolbox-0.0.16.dist-info/top_level.txt
cxs_logging_cxstoolbox-0.0.16.dist-info/RECORD
