Metadata-Version: 2.1
Name: cxs-logging-cxstoolbox
Version: 0.0.16
Summary: Send log from action node to csx toolbox log alerting
Home-page: https://github.com/pypa/sampleproject
Author: Si Le
Author-email: si@pypestream.com
License: UNKNOWN
Project-URL: Bug Tracker, https://github.com/pypa/sampleproject/issues
Platform: UNKNOWN
Classifier: Programming Language :: Python :: 3
Classifier: License :: OSI Approved :: MIT License
Classifier: Operating System :: OS Independent
Requires-Python: >=3.6
License-File: LICENSE
